[{"id":5,"key":"s5","title":"h5游戏平台分析系统","children":[{"id":19,"key":"s5g10050","title":"途游棋牌","children":[{"id":7,"key":"s5g10050a7","title":"H5数据分析","children":[{"id":701,"key":"s5g10050a7b701","title":"五分钟视图"},{"id":702,"key":"s5g10050a7b702","title":"指标趋势看盘"},{"id":703,"key":"s5g10050a7b703","title":"新用户留存率"},{"id":704,"key":"s5g10050a7b704","title":"五力模型"},{"id":705,"key":"s5g10050a7b705","title":"大R帐号"},{"id":706,"key":"s5g10050a7b706","title":"新用户注收比"}]}]},{"id":21,"key":"s5g10061","title":"全员加速中","children":[{"id":7,"key":"s5g10061a7","title":"H5数据分析","children":[{"id":701,"key":"s5g10061a7b701","title":"五分钟视图"},{"id":702,"key":"s5g10061a7b702","title":"指标趋势看盘"},{"id":703,"key":"s5g10061a7b703","title":"新用户留存率"},{"id":704,"key":"s5g10061a7b704","title":"五力模型"},{"id":705,"key":"s5g10061a7b705","title":"大R帐号"},{"id":706,"key":"s5g10061a7b706","title":"新用户注收比"}]}]},{"id":20,"key":"s5g1000","title":"H5游戏平台","children":[{"id":7,"key":"s5g1000a7","title":"H5数据分析","children":[{"id":701,"key":"s5g1000a7b701","title":"五分钟视图"},{"id":702,"key":"s5g1000a7b702","title":"指标趋势看盘"},{"id":703,"key":"s5g1000a7b703","title":"新用户留存率"},{"id":704,"key":"s5g1000a7b704","title":"五力模型"},{"id":705,"key":"s5g1000a7b705","title":"大R帐号"},{"id":706,"key":"s5g1000a7b706","title":"新用户注收比"},{"id":707,"key":"s5g1000a7b707","title":"h5平台汇总"}]}]},{"id":22,"key":"s5g10051","title":"少女H计划2","children":[{"id":7,"key":"s5g10051a7","title":"H5数据分析","children":[{"id":701,"key":"s5g10051a7b701","title":"五分钟视图"},{"id":702,"key":"s5g10051a7b702","title":"指标趋势看盘"},{"id":703,"key":"s5g10051a7b703","title":"新用户留存率"},{"id":704,"key":"s5g10051a7b704","title":"五力模型"},{"id":705,"key":"s5g10051a7b705","title":"大R帐号"},{"id":706,"key":"s5g10051a7b706","title":"新用户注收比"}]}]},{"id":23,"key":"s5g10063","title":"口袋妖怪联盟","children":[{"id":7,"key":"s5g10063a7","title":"H5数据分析","children":[{"id":701,"key":"s5g10063a7b701","title":"五分钟视图"},{"id":702,"key":"s5g10063a7b702","title":"指标趋势看盘"},{"id":703,"key":"s5g10063a7b703","title":"新用户留存率"},{"id":704,"key":"s5g10063a7b704","title":"五力模型"},{"id":705,"key":"s5g10063a7b705","title":"大R帐号"},{"id":706,"key":"s5g10063a7b706","title":"新用户注收比"}]}]},{"id":24,"key":"s5g10053","title":"新大主宰","children":[{"id":7,"key":"s5g10053a7","title":"H5数据分析","children":[{"id":701,"key":"s5g10053a7b701","title":"五分钟视图"},{"id":702,"key":"s5g10053a7b702","title":"指标趋势看盘"},{"id":703,"key":"s5g10053a7b703","title":"新用户留存率"},{"id":704,"key":"s5g10053a7b704","title":"五力模型"},{"id":705,"key":"s5g10053a7b705","title":"大R帐号"},{"id":706,"key":"s5g10053a7b706","title":"新用户注收比"}]}]},{"id":25,"key":"s5g10054","title":"神经猫","children":[{"id":7,"key":"s5g10054a7","title":"H5数据分析","children":[{"id":701,"key":"s5g10054a7b701","title":"五分钟视图"},{"id":702,"key":"s5g10054a7b702","title":"指标趋势看盘"},{"id":703,"key":"s5g10054a7b703","title":"新用户留存率"},{"id":704,"key":"s5g10054a7b704","title":"五力模型"},{"id":705,"key":"s5g10054a7b705","title":"大R帐号"},{"id":706,"key":"s5g10054a7b706","title":"新用户注收比"}]}]},{"id":26,"key":"s5g10055","title":"2048","children":[{"id":7,"key":"s5g10055a7","title":"H5数据分析","children":[{"id":701,"key":"s5g10055a7b701","title":"五分钟视图"},{"id":702,"key":"s5g10055a7b702","title":"指标趋势看盘"},{"id":703,"key":"s5g10055a7b703","title":"新用户留存率"},{"id":704,"key":"s5g10055a7b704","title":"五力模型"},{"id":705,"key":"s5g10055a7b705","title":"大R帐号"},{"id":706,"key":"s5g10055a7b706","title":"新用户注收比"}]}]},{"id":27,"key":"s5g10057","title":"幻城","children":[{"id":7,"key":"s5g10057a7","title":"H5数据分析","children":[{"id":701,"key":"s5g10057a7b701","title":"五分钟视图"},{"id":702,"key":"s5g10057a7b702","title":"指标趋势看盘"},{"id":703,"key":"s5g10057a7b703","title":"新用户留存率"},{"id":704,"key":"s5g10057a7b704","title":"五力模型"},{"id":705,"key":"s5g10057a7b705","title":"大R帐号"},{"id":706,"key":"s5g10057a7b706","title":"新用户注收比"}]}]},{"id":28,"key":"s5g10058","title":"美人心计","children":[{"id":7,"key":"s5g10058a7","title":"H5数据分析","children":[{"id":701,"key":"s5g10058a7b701","title":"五分钟视图"},{"id":702,"key":"s5g10058a7b702","title":"指标趋势看盘"},{"id":703,"key":"s5g10058a7b703","title":"新用户留存率"},{"id":704,"key":"s5g10058a7b704","title":"五力模型"},{"id":705,"key":"s5g10058a7b705","title":"大R帐号"},{"id":706,"key":"s5g10058a7b706","title":"新用户注收比"}]}]},{"id":29,"key":"s5g10059","title":"全民穿越之宫","children":[{"id":7,"key":"s5g10059a7","title":"H5数据分析","children":[{"id":701,"key":"s5g10059a7b701","title":"五分钟视图"},{"id":702,"key":"s5g10059a7b702","title":"指标趋势看盘"},{"id":703,"key":"s5g10059a7b703","title":"新用户留存率"},{"id":704,"key":"s5g10059a7b704","title":"五力模型"},{"id":705,"key":"s5g10059a7b705","title":"大R帐号"},{"id":706,"key":"s5g10059a7b706","title":"新用户注收比"}]}]},{"id":30,"key":"s5g10060","title":"愚公移山","children":[{"id":7,"key":"s5g10060a7","title":"H5数据分析","children":[{"id":701,"key":"s5g10060a7b701","title":"五分钟视图"},{"id":702,"key":"s5g10060a7b702","title":"指标趋势看盘"},{"id":703,"key":"s5g10060a7b703","title":"新用户留存率"},{"id":704,"key":"s5g10060a7b704","title":"五力模型"},{"id":705,"key":"s5g10060a7b705","title":"大R帐号"},{"id":706,"key":"s5g10060a7b706","title":"新用户注收比"}]}]}]}]